Gradle2YonghuZhinan/README.md
Gradle2YonghuZhinan/__init__.py
Gradle2YonghuZhinan/__main__.py
Gradle2YonghuZhinan/file.epub
Gradle2YonghuZhinan/index.html
Gradle2YonghuZhinan/css/__init__.py
Gradle2YonghuZhinan/css/annotations.css
Gradle2YonghuZhinan/css/main.css
Gradle2YonghuZhinan/css/normalize.css
Gradle2YonghuZhinan/css/popup.css
Gradle2YonghuZhinan/font/__init__.py
Gradle2YonghuZhinan/font/fontello.eot
Gradle2YonghuZhinan/font/fontello.svg
Gradle2YonghuZhinan/font/fontello.ttf
Gradle2YonghuZhinan/font/fontello.woff
Gradle2YonghuZhinan/img/__init__.py
Gradle2YonghuZhinan/img/annotator-glyph-sprite.png
Gradle2YonghuZhinan/img/annotator-icon-sprite.png
Gradle2YonghuZhinan/img/apple-touch-icon.png
Gradle2YonghuZhinan/img/cancelfullscreen.png
Gradle2YonghuZhinan/img/close.png
Gradle2YonghuZhinan/img/fullscreen.png
Gradle2YonghuZhinan/img/loader.gif
Gradle2YonghuZhinan/img/menu-icon.png
Gradle2YonghuZhinan/img/save.png
Gradle2YonghuZhinan/img/saved.png
Gradle2YonghuZhinan/img/settings-s.png
Gradle2YonghuZhinan/img/settings.png
Gradle2YonghuZhinan/img/star.png
Gradle2YonghuZhinan/js/__init__.py
Gradle2YonghuZhinan/js/epub.js
Gradle2YonghuZhinan/js/epub.min.js
Gradle2YonghuZhinan/js/epub.min.map
Gradle2YonghuZhinan/js/hooks.min.js
Gradle2YonghuZhinan/js/hooks.min.map
Gradle2YonghuZhinan/js/reader.js
Gradle2YonghuZhinan/js/reader.js.map
Gradle2YonghuZhinan/js/reader.min.js
Gradle2YonghuZhinan/js/reader.min.map
Gradle2YonghuZhinan/js/hooks/__init__.py
Gradle2YonghuZhinan/js/hooks/extensions/__init__.py
Gradle2YonghuZhinan/js/hooks/extensions/highlight.js
Gradle2YonghuZhinan/js/libs/__init__.py
Gradle2YonghuZhinan/js/libs/jquery.min.js
Gradle2YonghuZhinan/js/libs/localforage.min.js
Gradle2YonghuZhinan/js/libs/screenfull.js
Gradle2YonghuZhinan/js/libs/screenfull.min.js
Gradle2YonghuZhinan/js/libs/zip.min.js
Gradle2YonghuZhinan/js/plugins/__init__.py
Gradle2YonghuZhinan/js/plugins/hypothesis.js
Gradle2YonghuZhinan/js/plugins/search.js
gradle_2_yonghu_zhinan-2024.3.1.0.dist-info/METADATA
gradle_2_yonghu_zhinan-2024.3.1.0.dist-info/WHEEL
gradle_2_yonghu_zhinan-2024.3.1.0.dist-info/entry_points.txt
gradle_2_yonghu_zhinan-2024.3.1.0.dist-info/top_level.txt
gradle_2_yonghu_zhinan-2024.3.1.0.dist-info/RECORD
